{
  "format_version": "1.12",
  "minecraft:recipe_shaped": {
    "description": {
      "identifier": "base:diamond_nuggets"
    },
    "tags": [
      "crafting_table"
    ],
    "pattern": [
      "aaa",
      "aaa",
      "aaa"
    ],
    "key": {
      "a": {
        "item": "base:diamond_nugget"
      },
      "b": {
        "item": "minecraft:stick"
      },
      "c": {
        "item": "base:stick"
      },
      "d": {
        "item": "minecraft:iron_nugget"
      }
    },
    "result": {
      "item": "minecraft:diamond",
      "data": 0,
      "count": 1
    }
  }
}