{
	"file_path": "C:\\Users\\Hp\\AppData\\Local\\Packages\\Microsoft.MinecraftUWP_8wekyb3d8bbwe\\LocalState\\games\\com.mojang\\development_resource_packs\\Mo'creatures bedrock §a[RP]\\entity\\hellrat.json",
	"file_type": "client_entity",
	"format_version": 1,
	"file_uuid": "a14e846c_29a5_488e_b24f_bfba5bdd1e85",
	"file_version": 6,
	"cache_content": {
		"children": [
			{
				"data": "1.10.0",
				"key": "format_version"
			},
			{
				"open": {
					"format_version": "1.10.0",
					"minecraft:client_entity": {
						"description": {
							"identifier": "mocreatures:hellrat",
							"min_engine_version": "1.8.0",
							"materials": {
								"default": "armor_stand"
							},
							"textures": {
								"default": "textures/entity/hellrat/hellrat1",
								"fase1": "textures/entity/hellrat/hellrat1"
							},
							"animations": {
								"walk": "animation.rat.walk",
								"look_at_target": "animation.common.look_at_target"
							},
							"scripts": {
								"animate": [
									{
										"walk": "query.modified_move_speed"
									},
									"look_at_target"
								]
							},
							"geometry": {
								"default": "geometry.rat"
							},
							"render_controllers": [
								"controller.render.hellrat"
							],
							"spawn_egg": {
								"texture": "rats_spawn_egg",
								"texture_index": 1
							}
						}
					}
				},
				"key": "minecraft:client_entity",
				"children": [
					{
						"open": {
							"description": {
								"identifier": "mocreatures:hellrat",
								"min_engine_version": "1.8.0",
								"materials": {
									"default": "armor_stand"
								},
								"textures": {
									"default": "textures/entity/hellrat/hellrat1",
									"fase1": "textures/entity/hellrat/hellrat1"
								},
								"animations": {
									"walk": "animation.rat.walk",
									"look_at_target": "animation.common.look_at_target"
								},
								"scripts": {
									"animate": [
										{
											"walk": "query.modified_move_speed"
										},
										"look_at_target"
									]
								},
								"geometry": {
									"default": "geometry.rat"
								},
								"render_controllers": [
									"controller.render.hellrat"
								],
								"spawn_egg": {
									"texture": "rats_spawn_egg",
									"texture_index": 1
								}
							}
						},
						"key": "description",
						"is_minified": true,
						"children": {
							"identifier": "mocreatures:hellrat",
							"min_engine_version": "1.8.0",
							"materials": {
								"default": "armor_stand"
							},
							"textures": {
								"default": "textures/entity/hellrat/hellrat1",
								"fase1": "textures/entity/hellrat/hellrat1"
							},
							"animations": {
								"walk": "animation.rat.walk",
								"look_at_target": "animation.common.look_at_target"
							},
							"scripts": {
								"animate": [
									{
										"walk": "query.modified_move_speed"
									},
									"look_at_target"
								]
							},
							"geometry": {
								"default": "geometry.rat"
							},
							"render_controllers": [
								"controller.render.hellrat"
							],
							"spawn_egg": {
								"texture": "rats_spawn_egg",
								"texture_index": 1
							}
						}
					}
				]
			}
		]
	}
}